broadsteel_datascience/__init__.py
broadsteel_datascience/broadsteel_datascience.py
broadsteel_datascience/cli.py
broadsteel_datascience-0.1.0.dist-info/AUTHORS.rst
broadsteel_datascience-0.1.0.dist-info/LICENSE
broadsteel_datascience-0.1.0.dist-info/METADATA
broadsteel_datascience-0.1.0.dist-info/WHEEL
broadsteel_datascience-0.1.0.dist-info/entry_points.txt
broadsteel_datascience-0.1.0.dist-info/top_level.txt
broadsteel_datascience-0.1.0.dist-info/RECORD
