Metadata-Version: 2.1
Name: broadsteel-datascience
Version: 0.1.0
Summary: BroadSteel_DataScience
Home-page: https://github.com/jirvingphd/broadsteel_datascience
Author: James M. Irving, Michael V. Moravetz
Author-email: james.irving.phd@outlook.com
License: MIT license
Keywords: broadsteel_datascience
Platform: UNKNOWN
Classifier: Development Status :: 2 - Pre-Alpha
Classifier: Intended Audience :: Developers
Classifier: License :: OSI Approved :: MIT License
Classifier: Natural Language :: English
Classifier: Programming Language :: Python :: 2
Classifier: Programming Language :: Python :: 2.7
Classifier: Programming Language :: Python :: 3
Classifier: Programming Language :: Python :: 3.4
Classifier: Programming Language :: Python :: 3.5
Classifier: Programming Language :: Python :: 3.6
Classifier: Programming Language :: Python :: 3.7
Requires-Dist: Click (>=6.0)
Requires-Dist: numpy
Requires-Dist: pandas
Requires-Dist: seaborn
Requires-Dist: matplotlib
Requires-Dist: sklearn
Requires-Dist: pydotplus
Requires-Dist: scipy
Requires-Dist: xgboost
Requires-Dist: IPython
